{"remainingRequest":"C:\\Users\\Michael\\VSCodeProjects\\mern-stack-starter-pack\\node_modules\\babel-loader\\lib\\index.js??ref--4-1!C:\\Users\\Michael\\VSCodeProjects\\mern-stack-starter-pack\\node_modules\\eslint-loader\\index.js!C:\\Users\\Michael\\VSCodeProjects\\mern-stack-starter-pack\\node_modules\\core-js\\modules\\_string-context.js","dependencies":[{"path":"C:\\Users\\Michael\\VSCodeProjects\\mern-stack-starter-pack\\node_modules\\core-js\\modules\\_string-context.js","mtime":499162500000},{"path":"C:\\Users\\Michael\\VSCodeProjects\\mern-stack-starter-pack\\node_modules\\cache-loader\\dist\\cjs.js","mtime":499162500000},{"path":"C:\\Users\\Michael\\VSCodeProjects\\mern-stack-starter-pack\\node_modules\\babel-loader\\lib\\index.js","mtime":499162500000},{"path":"C:\\Users\\Michael\\VSCodeProjects\\mern-stack-starter-pack\\node_modules\\eslint-loader\\index.js","mtime":499162500000}],"contextDependencies":[],"result":["// helper for String#{startsWith, endsWith, includes}\nvar isRegExp = require('./_is-regexp');\n\nvar defined = require('./_defined');\n\nmodule.exports = function (that, searchString, NAME) {\n  if (isRegExp(searchString)) throw TypeError('String#' + NAME + \" doesn't accept regex!\");\n  return String(defined(that));\n};",null]}